{
	"version": "5.3.0",
	"objects": [
		{
			"type": "rect",
			"version": "5.3.0",
			"originX": "left",
			"originY": "top",
			"left": 566,
			"top": -159,
			"width": 300,
			"height": 300,
			"fill": "white",
			"stroke": null,
			"strokeWidth": 1,
			"strokeDashArray": null,
			"strokeLineCap": "butt",
			"strokeDashOffset": 0,
			"strokeLineJoin": "miter",
			"strokeUniform": false,
			"strokeMiterLimit": 4,
			"scaleX": 1,
			"scaleY": 1,
			"angle": 0,
			"flipX": false,
			"flipY": false,
			"opacity": 1,
			"shadow": {
				"color": "rgba(0,0,0,0.8)",
				"blur": 5,
				"offsetX": 0,
				"offsetY": 0,
				"affectStroke": false,
				"nonScaling": false
			},
			"visible": true,
			"backgroundColor": "",
			"fillRule": "nonzero",
			"paintFirst": "fill",
			"globalCompositeOperation": "source-over",
			"skewX": 0,
			"skewY": 0,
			"rx": 0,
			"ry": 0,
			"name": "clip",
			"selectable": false,
			"hasControls": false
		},
		{
			"type": "image",
			"version": "5.3.0",
			"originX": "left",
			"originY": "top",
			"left": 671.34,
			"top": -69.93,
			"width": 1724,
			"height": 1363,
			"fill": "rgb(0,0,0)",
			"stroke": null,
			"strokeWidth": 0,
			"strokeDashArray": null,
			"strokeLineCap": "butt",
			"strokeDashOffset": 0,
			"strokeLineJoin": "miter",
			"strokeUniform": false,
			"strokeMiterLimit": 4,
			"scaleX": 0.07,
			"scaleY": 0.07,
			"angle": 0,
			"flipX": false,
			"flipY": false,
			"opacity": 1,
			"shadow": null,
			"visible": true,
			"backgroundColor": "",
			"fillRule": "nonzero",
			"paintFirst": "fill",
			"globalCompositeOperation": "source-over",
			"skewX": 0,
			"skewY": 0,
			"cropX": 0,
			"cropY": 0,
			"selectable": true,
			"hasControls": true,
			"src": "https://utfs.io/f/oTHHZ2dBnWVze53qpVytaXS0Efs17oM256Vrlt3qYuzBJeNH",
			"crossOrigin": "anonymous",
			"filters": []
		},
		{
			"type": "image",
			"version": "5.3.0",
			"originX": "left",
			"originY": "top",
			"left": 758.46,
			"top": -113.78,
			"width": 352,
			"height": 408,
			"fill": "rgb(0,0,0)",
			"stroke": null,
			"strokeWidth": 0,
			"strokeDashArray": null,
			"strokeLineCap": "butt",
			"strokeDashOffset": 0,
			"strokeLineJoin": "miter",
			"strokeUniform": false,
			"strokeMiterLimit": 4,
			"scaleX": 0.09,
			"scaleY": 0.09,
			"angle": 0,
			"flipX": false,
			"flipY": false,
			"opacity": 1,
			"shadow": null,
			"visible": true,
			"backgroundColor": "",
			"fillRule": "nonzero",
			"paintFirst": "fill",
			"globalCompositeOperation": "source-over",
			"skewX": 0,
			"skewY": 0,
			"cropX": 0,
			"cropY": 0,
			"selectable": true,
			"hasControls": true,
			"src": "https://utfs.io/f/oTHHZ2dBnWVzbQPcvyaugyUdhTNYk9nQsExBDlGI6efFoLHV",
			"crossOrigin": "anonymous",
			"filters": []
		},
		{
			"type": "image",
			"version": "5.3.0",
			"originX": "left",
			"originY": "top",
			"left": 624.56,
			"top": -94.98,
			"width": 1835,
			"height": 1308,
			"fill": "rgb(0,0,0)",
			"stroke": null,
			"strokeWidth": 0,
			"strokeDashArray": null,
			"strokeLineCap": "butt",
			"strokeDashOffset": 0,
			"strokeLineJoin": "miter",
			"strokeUniform": false,
			"strokeMiterLimit": 4,
			"scaleX": 0.07,
			"scaleY": 0.07,
			"angle": 0,
			"flipX": false,
			"flipY": false,
			"opacity": 1,
			"shadow": null,
			"visible": true,
			"backgroundColor": "",
			"fillRule": "nonzero",
			"paintFirst": "fill",
			"globalCompositeOperation": "source-over",
			"skewX": 0,
			"skewY": 0,
			"cropX": 0,
			"cropY": 0,
			"selectable": true,
			"hasControls": true,
			"src": "https://utfs.io/f/oTHHZ2dBnWVz707TJq9DTY65tfi0HcXbqkPlZyso2hjRJpWe",
			"crossOrigin": "anonymous",
			"filters": []
		},
		{
			"type": "textbox",
			"version": "5.3.0",
			"originX": "left",
			"originY": "top",
			"left": 605.42,
			"top": 34.62,
			"width": 869.69,
			"height": 90.4,
			"fill": "rgba(0, 0, 50, 1)",
			"stroke": null,
			"strokeWidth": 1,
			"strokeDashArray": null,
			"strokeLineCap": "butt",
			"strokeDashOffset": 0,
			"strokeLineJoin": "miter",
			"strokeUniform": false,
			"strokeMiterLimit": 4,
			"scaleX": 0.27,
			"scaleY": 0.27,
			"angle": 0,
			"flipX": false,
			"flipY": false,
			"opacity": 1,
			"shadow": null,
			"visible": true,
			"backgroundColor": "",
			"fillRule": "nonzero",
			"paintFirst": "fill",
			"globalCompositeOperation": "source-over",
			"skewX": 0,
			"skewY": 0,
			"fontFamily": "Verdana",
			"fontWeight": 700,
			"fontSize": 80,
			"text": "{{BRAND_NAME}}",
			"underline": false,
			"overline": false,
			"linethrough": false,
			"textAlign": "center",
			"fontStyle": "normal",
			"lineHeight": 1.16,
			"textBackgroundColor": "",
			"charSpacing": 0,
			"styles": [
				{
					"start": 0,
					"end": 14,
					"style": {
						"stroke": null,
						"strokeWidth": 1,
						"fill": "rgba(0, 0, 50, 1)",
						"fontFamily": "Verdana",
						"fontSize": 80,
						"fontWeight": 700,
						"fontStyle": "normal",
						"underline": false,
						"overline": false,
						"linethrough": false,
						"deltaY": 0,
						"textBackgroundColor": ""
					}
				}
			],
			"direction": "ltr",
			"path": null,
			"pathStartOffset": 0,
			"pathSide": "left",
			"pathAlign": "baseline",
			"minWidth": 20,
			"splitByGrapheme": false,
			"selectable": true,
			"hasControls": true,
			"editable": true
		},
		{
			"type": "textbox",
			"version": "5.3.0",
			"originX": "left",
			"originY": "top",
			"left": 701.13,
			"top": 62.66,
			"width": 258.33,
			"height": 49.72,
			"fill": "rgba(102, 203, 0, 1)",
			"stroke": null,
			"strokeWidth": 1,
			"strokeDashArray": null,
			"strokeLineCap": "butt",
			"strokeDashOffset": 0,
			"strokeLineJoin": "miter",
			"strokeUniform": false,
			"strokeMiterLimit": 4,
			"scaleX": 0.23,
			"scaleY": 0.23,
			"angle": 0,
			"flipX": false,
			"flipY": false,
			"opacity": 1,
			"shadow": null,
			"visible": true,
			"backgroundColor": "",
			"fillRule": "nonzero",
			"paintFirst": "fill",
			"globalCompositeOperation": "source-over",
			"skewX": 0,
			"skewY": 0,
			"fontFamily": "Arial",
			"fontWeight": 600,
			"fontSize": 44,
			"text": "{{TAGLINE}}",
			"underline": false,
			"overline": false,
			"linethrough": false,
			"textAlign": "center",
			"fontStyle": "normal",
			"lineHeight": 1.16,
			"textBackgroundColor": "",
			"charSpacing": 0,
			"styles": [],
			"direction": "ltr",
			"path": null,
			"pathStartOffset": 0,
			"pathSide": "left",
			"pathAlign": "baseline",
			"minWidth": 20,
			"splitByGrapheme": false,
			"selectable": true,
			"hasControls": true,
			"editable": true
		}
	],
	"clipPath": {
		"type": "rect",
		"version": "5.3.0",
		"originX": "left",
		"originY": "top",
		"left": 566,
		"top": -159,
		"width": 300,
		"height": 300,
		"fill": "white",
		"stroke": null,
		"strokeWidth": 1,
		"strokeDashArray": null,
		"strokeLineCap": "butt",
		"strokeDashOffset": 0,
		"strokeLineJoin": "miter",
		"strokeUniform": false,
		"strokeMiterLimit": 4,
		"scaleX": 1,
		"scaleY": 1,
		"angle": 0,
		"flipX": false,
		"flipY": false,
		"opacity": 1,
		"shadow": {
			"color": "rgba(0,0,0,0.8)",
			"blur": 5,
			"offsetX": 0,
			"offsetY": 0,
			"affectStroke": false,
			"nonScaling": false
		},
		"visible": true,
		"backgroundColor": "",
		"fillRule": "nonzero",
		"paintFirst": "fill",
		"globalCompositeOperation": "source-over",
		"skewX": 0,
		"skewY": 0,
		"rx": 0,
		"ry": 0,
		"selectable": true,
		"hasControls": true
	}
}